Workbook

Sheet Matriz Ckeck LIst
D2: INTEGRANTES: | E2: Laínez Suárez Ricardo Andrés, Padilla Triviño Marco Adrian, Andino Martínez Nelson David
C3: MATRIZ PARA COMPROBACIÓN REQUERIMIENTOS DE CALIDAD DE PROYECTO ACADEMICO
D5: SISTEMA: | E5: SISTEMA DE GESTIÓN DE PEDIDOS DEL RESTAURANTE BOCATTO VALLEY
F6: Requerimientos Funcionales
B7: Nº | C7: CRITERIOS DE CALIDAD (Documento/Requerimientos) | E7: Status Nivel de Acuerdo | F7: CU 0-0 Autenticar en el sistema | G7: Status Nivel de Acuerdo | H7: CU 0-1 Tomar pedido en mesa | I7: Status Nivel de Acuerdo | J7: CU 0-2 Tomar pedido telefónico | K7: Status Nivel de Acuerdo | L7: 100 | M7: CU 0-3 Realizar pedido por QR | N7: Status Nivel de Acuerdo | O7: CU 0-4 Gestionar preparación del pedido | P7: Status Nivel de Acuerdo | Q7: CU 0-5 Cobrar pedido en la caja | R7: Status Nivel de Acuerdo | S7: CU 0-6 Consultar estado de pedido | T7: Status Nivel de Acuerdo | U7: CU 0-7 Administrar configuración del sistema
L8: 0
B9: 1 | C9: Agreed | E9: OK | F9: 1. Videoconferencia de la entrevista 2. Minuta de la entrevista 3. Aceptación por videoconferencia | G9: OK | H9: 1. Videoconferencia de la entrevista 2. Minuta de la entrevista 3. Aceptación por videoconferencia | I9: OK | J9: 1. Videoconferencia y minuta de la entrevista con el propietario del restaurante. 2. Acta de la sesión de brainstorming con el personal operativo. 3. Video de aceptación en el que el cliente expresa su conformidad con la ERS final. | K9: OK | L9: 1 | M9: 1. Videoconferencia y minuta de la entrevista con el propietario del restaurante. 2. Acta de la sesión de brainstorming con el personal operativo. 3. Video de aceptación en el que el cliente expresa su conformidad con la ERS final. | N9: OK | O9: 1. Videoconferencia de la entrevista 2. Minuta de la entrevista 3. Aceptación por videoconferencia | P9: OK | Q9: 1. Videoconferencia y minuta de la entrevista con el propietario del restaurante. 2. Acta de la sesión de brainstorming con el personal operativo. 3. Video de aceptación en el que el cliente expresa su conformidad con la ERS final. | R9: OK | S9: 1. Videoconferencia de la entrevista 2. Minuta de la entrevista 3. Aceptación por videoconferencia | T9: OK | U9: 1. Videoconferencia de la entrevista 2. Minuta de la entrevista 3. Aceptación por videoconferencia
B10: 2 | C10: Ranked | E10: OK | F10: 1. En la descripción del caso de Uso se especifica la prioridad Alta | G10: OK | H10: 1. En la descripción del caso de Uso se especifica la prioridad Alta | I10: OK | J10: 1. RF-03 tiene prioridad Alta/Esencial. 2. El CU 0-2 es de tipo primario y esencial. | K10: OK | M10: 1. RF-04 tiene prioridad Alta/Esencial. 2. El CU 0-3 es de tipo primario y esencial. | N10: OK | O10: 1. En la descripción del caso de Uso se especifica la prioridad Alta | P10: OK | Q10: 1. RF-06 tiene prioridad Alta/Esencial. 2. El CU 0-5 es de tipo primario y esencial. | R10: OK | S10: 1. En la descripción del caso de Uso se especifica la prioridad Alta | T10: OK | U10: 1. En la descripción del caso de Uso se especifica la prioridad Alta
B11: 3 | C11: Unambiguos | E11: OK | F11: 1. Redacción en lenguaje claro. 2. El tutor y el equipo interpretan de igual manera el caso de uso | G11: OK | H11: 1. Redacción en lenguaje claro. 2. El tutor y el equipo interpretan de igual manera el caso de uso | I11: NOK | J11: 1. El CU 0-2 indica que el operador registra "los datos necesarios para la entrega o retiro (según aplique)" y el RF-03 habla de "datos básicos del cliente", sin precisar cuáles son. 2. El resto de la redacción (productos, cantidades, observaciones, estado "pendiente") es claro. | K11: OK | M11: 1. Redacción en lenguaje claro en el CU 0-3 y en el RF-04. 2. Términos como "Código QR" y "Menú digital" están definidos con ejemplos en el glosario. | N11: NOK | O11: 1. Redacción en lenguaje claro. 2. El tutor y el equipo interpretan de igual manera el caso de uso | P11: OK | Q11: 1. Redacción en lenguaje claro en el CU 0-5 y en el RF-06: búsqueda por mesa, verificación del total y método de pago (efectivo o digital/transferencia). 2. El tutor y el equipo interpretan de igual manera el caso de uso. | R11: NOK | S11: 1. Redacción en lenguaje claro. 2. El tutor y el equipo interpretan de igual manera el caso de uso | T11: NOK | U11: 1. Redacción en lenguaje claro. 2. El tutor y el equipo interpretan de igual manera el caso de uso
B12: 4 | C12: Valid and up-to date | E12: OK | F12: 1. No se han incorporado los últimos cambios pedidos luego del feedback realizado por el cliente | G12: OK | H12: 1. No se han incorporado los últimos cambios pedidos luego del feedback realizado por el cliente | I12: OK | J12: 1. Corresponde a la versión final de la ERS (Rev. 1), aceptada por el cliente. 2. El alcance (sección 1.2) es coherente con la Propuesta 1 y con los casos de uso. | K12: OK | M12: 1. Corresponde a la versión final de la ERS (Rev. 1), aceptada por el cliente. 2. El alcance (sección 1.2) es coherente con la Propuesta 1 y con los casos de uso. | N12: NOK | O12: 1. No se han incorporado los últimos cambios pedidos luego del feedback realizado por el cliente | P12: OK | Q12: 1. Corresponde a la versión final de la ERS (Rev. 1), aceptada por el cliente. 2. El alcance (sección 1.2) es coherente con la Propuesta 1 y con los casos de uso. | R12: NOK | S12: 1. No se han incorporado los últimos cambios pedidos luego del feedback realizado por el cliente | T12: NOK | U12: 1. No se han incorporado los últimos cambios pedidos luego del feedback realizado por el cliente
B13: 5 | C13: Correct | E13: OK | F13: 1. Está alineado con los objetivos del sistema. 2. Refleja lo que realmente necesita el cliente. | G13: OK | H13: 1. Está alineado con los objetivos del sistema. 2. Refleja lo que realmente necesita el cliente. | I13: OK | J13: 1. Está alineado con el objetivo de evitar errores al anotar las órdenes recibidas por teléfono. 2. Responde al alcance "Registro de pedidos telefónicos" (sección 1.2) y al rol de operador de llamadas (sección 2.3). | K13: OK | M13: 1. Está alineado con el objetivo de automatizar el flujo de información desde la toma del pedido. 2. Responde al alcance "Registro de pedidos mediante QR" (sección 1.2). | N13: OK | O13: 1. Está alineado con los objetivos del sistema. 2. Refleja lo que realmente necesita el cliente. | P13: OK | Q13: 1. Está alineado con el problema de errores en el cobro por acumulación de pedidos. 2. Responde al alcance "Cobro y registro de pagos en la caja" (sección 1.2) sin integrar un sistema de pagos externo (sección 2.1). | R13: OK | S13: 1. Está alineado con los objetivos del sistema. 2. Refleja lo que realmente necesita el cliente. | T13: OK | U13: 1. Está alineado con los objetivos del sistema. 2. Refleja lo que realmente necesita el cliente.
B14: 6 | C14: Consisten | E14: OK | F14: 1. Documentación basada en modelos: Diagrama de Casos de Uso 2. Usa términos definidos previamente. | G14: OK | H14: 1. Documentación basada en modelos: Diagrama de Casos de Uso 2. Usa términos definidos previamente. | I14: NOK | J14: 1. El CU 0-5 y el RF-06 solo permiten buscar el pedido por número de mesa, mientras que un pedido telefónico no tiene mesa asociada. 2. Usa términos del glosario y documentación basada en casos de uso. | K14: OK | M14: 1. Documentación basada en modelos: casos de uso (sección 2.2). 2. Usa términos del glosario de forma uniforme y el estado inicial "pendiente" coincide con los demás canales de pedido. | N14: NOK | O14: 1. Documentación basada en modelos: Diagrama de Casos de Uso 2. Usa términos definidos previamente. | P14: NOK | Q14: 1. El CU 0-5 indica que el sistema habilita "listo para entregar" después del pago, mientras que el CU 0-4 y el RF-05 asignan ese estado al cocinero. 2. El estado "pagado" no aparece en la secuencia de estados del RF-05 ni del CU 0-6. 3. La búsqueda solo por mesa no cubre los pedidos telefónicos (CU 0-2). | R14: NOK | S14: 1. Documentación basada en modelos: Diagrama de Casos de Uso 2. Usa términos definidos previamente. | T14: NOK | U14: 1. Documentación basada en modelos: Diagrama de Casos de Uso 2. Usa términos definidos previamente.
B15: 7 | C15: Verifiable | E15: NOK | F15: 1. Requisito Medible 2. Falta Casos de Prueba | G15: NOK | H15: 1. Requisito Medible 2. Falta Casos de Prueba | I15: OK | J15: 1. Requisito medible: pedido con al menos un producto, datos del cliente registrados y estado inicial "pendiente". 2. Faltan casos de prueba. | K15: OK | M15: 1. Requisito medible: QR asociado a una mesa, pedido con al menos un producto y estado inicial "pendiente". 2. Faltan casos de prueba. | N15: OK | O15: 1. Requisito Medible 2. Falta Casos de Prueba | P15: OK | Q15: 1. Requisito medible: el cobro solo se permite si el pedido está listo y el pedido queda marcado como "pagado". 2. Faltan casos de prueba. | R15: OK | S15: 1. Requisito Medible 2. Falta Casos de Prueba | T15: OK | U15: 1. Requisito Medible 2. Falta Casos de Prueba
B16: 8 | C16: Realizable | E16: OK | F16: 1. Funcionalidad tomada en cuenta dentro de la estimación del costo del proyecto (900$) 2. No se ha desarrollado | G16: OK | H16: 1. Funcionalidad tomada en cuenta dentro de la estimación del costo del proyecto (900$) 2. No se ha desarrollado | I16: OK | J16: 1. Funcionalidad considerada en la estimación del proyecto (144 horas por integrante, costeo por hora según el rol). 2. Tecnologías y hardware mínimo definidos en la ERS (secciones 3.1.6 a 3.1.11): React + Vite, Node.js con Express, servicios REST con JSON. 3. Aún no se ha desarrollado. | K16: OK | M16: 1. Funcionalidad considerada en la estimación del proyecto (144 horas por integrante, costeo por hora según el rol). 2. Tecnologías y hardware mínimo definidos en la ERS (secciones 3.1.6 a 3.1.11): React + Vite, Node.js con Express, servicios REST con JSON. 3. Aún no se ha desarrollado. | N16: OK | O16: 1. Funcionalidad tomada en cuenta dentro de la estimación del costo del proyecto (900$) 2. No se ha desarrollado | P16: OK | Q16: 1. Funcionalidad considerada en la estimación del proyecto (144 horas por integrante, costeo por hora según el rol). 2. Tecnologías y hardware mínimo definidos en la ERS (secciones 3.1.6 a 3.1.11): React + Vite, Node.js con Express, servicios REST con JSON. 3. Aún no se ha desarrollado. | R16: OK | S16: 1. Funcionalidad tomada en cuenta dentro de la estimación del costo del proyecto (900$) 2. No se ha desarrollado | T16: OK | U16: 1. Funcionalidad tomada en cuenta dentro de la estimación del costo del proyecto (900$) 2. No se ha desarrollado
B17: 9 | C17: Traceable | E17: OK | F17: 1. Es claro el origen del requisito y sus relaciones con otros requisitos (matriz de trazabilidad cliente/casos de uso y casos de uso/casos de uso) 2. Cuenta con un identificador único | G17: OK | H17: 1. Es claro el origen del requisito y sus relaciones con otros requisitos (matriz de trazabilidad cliente/casos de uso y casos de uso/casos de uso) 2. Cuenta con un identificador único | I17: OK | J17: 1. RF-03 indica su fuente: CU 0-2 y CU 2.1 Registrar pedido telefónico. 2. Cuenta con código único (RF-03 / CU 0-2) y se relaciona con 3.2.5 y 3.2.6 (Tomar y Registrar pedido telefónico) y con el envío a cocina. | K17: OK | M17: 1. RF-04 indica su fuente: CU 0-3, CU 3.1, CU 3.2 y CU 3.3. 2. Se relaciona con 3.2.7 a 3.2.10 (Ver menú digital, Registrar pedido por QR y Agregar observaciones) y con RF-08 (gestión de QR y menú). | N17: OK | O17: 1. Es claro el origen del requisito y sus relaciones con otros requisitos (matriz de trazabilidad cliente/casos de uso y casos de uso/casos de uso) 2. Cuenta con un identificador único | P17: OK | Q17: 1. RF-06 indica su fuente: CU 0-5, CU 5.1 y CU 5.2. 2. Se relaciona con 3.2.14 a 3.2.18 (Buscar pedido por mesa, Cobrar pedido, Marcar pedido como pagado y Habilitar pedido para entrega). | R17: OK | S17: 1. Es claro el origen del requisito y sus relaciones con otros requisitos (matriz de trazabilidad cliente/casos de uso y casos de uso/casos de uso) 2. Cuenta con un identificador único | T17: OK | U17: 1. Es claro el origen del requisito y sus relaciones con otros requisitos (matriz de trazabilidad cliente/casos de uso y casos de uso/casos de uso) 2. Cuenta con un identificador único
B18: 10 | C18: Complete | E18: OK | F18: 1. Contiene toda la información necesaria (entradas, salidas, precondiciones, postcondiciones) para entender y diseñar la función. 2. Describe completamente la funcionalidad esperada. | G18: OK | H18: 1. Contiene toda la información necesaria (entradas, salidas, precondiciones, postcondiciones) para entender y diseñar la función. 2. Describe completamente la funcionalidad esperada. | I18: OK | J18: 1. Contiene actor, entradas (productos, cantidades, datos de entrega o retiro, observaciones), validación y salida (pedido con estado "pendiente" enviado a cocina). 2. Describe completamente la funcionalidad esperada del registro telefónico. | K18: OK | M18: 1. Contiene actor, escaneo del QR, identificación de la mesa, menú con precios y promociones, observaciones opcionales y registro con estado "pendiente". 2. Restricción asociada definida: el cliente requiere un dispositivo con cámara y navegador (sección 2.4). | N18: OK | O18: 1. Contiene toda la información necesaria (entradas, salidas, precondiciones, postcondiciones) para entender y diseñar la función. 2. Describe completamente la funcionalidad esperada. | P18: OK | Q18: 1. Contiene actor, entradas (número de mesa, método de pago), validación (pedido listo) y salidas (pedido "pagado" y habilitado para entrega). 2. Describe completamente la funcionalidad esperada del cobro. | R18: OK | S18: 1. Contiene toda la información necesaria (entradas, salidas, precondiciones, postcondiciones) para entender y diseñar la función. 2. Describe completamente la funcionalidad esperada. | T18: OK | U18: 1. Contiene toda la información necesaria (entradas, salidas, precondiciones, postcondiciones) para entender y diseñar la función. 2. Describe completamente la funcionalidad esperada.
B19: 11 | C19: Understandability | E19: OK | F19: 1. Se involucra al cliente 2. Existe glosario de términos | G19: OK | H19: 1. Se involucra al cliente 2. Existe glosario de términos | I19: OK | J19: 1. Se involucró al cliente y al personal operativo en la elicitación. 2. Uso de términos respaldado por el glosario de definiciones, acrónimos y abreviaturas (sección 1.4). | K19: OK | M19: 1. Se involucró al cliente y al personal operativo en la elicitación. 2. Uso de términos respaldado por el glosario de definiciones, acrónimos y abreviaturas (sección 1.4). | N19: OK | O19: 1. Se involucra al cliente 2. Existe glosario de términos | P19: OK | Q19: 1. Se involucró al cliente y al personal operativo en la elicitación. 2. Uso de términos respaldado por el glosario de definiciones, acrónimos y abreviaturas (sección 1.4). | R19: OK | S19: 1. Se involucra al cliente 2. Existe glosario de términos | T19: OK | U19: 1. Se involucra al cliente 2. Existe glosario de términos

Sheet LISTA DE COMPROBACION - CU0-0
B1: SISTEMA: | C1: SISTEMA DE GESTIÓN DE PEDIDOS DEL RESTAURANTE BOCATTO VALLEY
B2: FECHA: | C2: 46300
B3: AUTOR: | C3: Laínez Suárez Ricardo Andrés
B4: REQUERIMIENTOS EVALUADOS : | C4: CU 0-0 Autenticar en el sistema
A6: CONTENIDO
A7: No. | B7: Pregunta | C7: SI | D7: NO
A8: 1 | B8: Todos los requerimientos relevantes se han documentado? | C8: X
A9: 2 | B9: Se han implementado las funciones requeridas? | C9: X
A10: 3 | B10: Existe algún mecanismo que permita seguir el impacto de dicho requerimiento a lo largo del resto de las actividades del ciclo productivo.? | C10: X
A11: 4 | B11: El origen de cada requerimento individual está claro ? | C11: X
A12: 5 | B12: Que tan facil es devolverse a los requerimientos? | C12: X
A13: 6 | B13: Los requerimientos reflejan las necesidades y deseos del cliente? | C13: X
A14: 7 | B14: No hay contradicciones entre los requerimientos? | D14: X
A15: 8 | B15: El requerimiento que se esta especificando contribuye a alcanzar un objetivo definido ? | C15: X
A16: 9 | B16: Existe un proceso acotado (en plazo y presupuesto) que permita determinar que el sistema construido satisface lo descrito en el propio requerimiento? | C16: x
A17: SUMATORIA: | C17: =COUNTA('LISTA DE COMPROBACION - CU0-0'!$C$8:$C$16) -> 8 | D17: =COUNTA('LISTA DE COMPROBACION - CU0-0'!$D$8:$D$16) -> 1
A18: PORCENTAJE : | C18: =C17/9 -> 0.88888889 | D18: =D17/9 -> 0.11111111
A20: DOCUMENTACIÓN
A21: No. | B21: Pregunta | C21: SI | D21: NO
A22: 1 | B22: Aplica un estandar para la documetación de requerimiento? | C22: X
A23: 2 | B23: Cumple con la estructura definida por el estandar? | C23: X
A24: 3 | B24: Utiliza un Glosario de términos normalizado? | C24: X
A25: 4 | B25: Los requerimientos Funcionales estan sujetos a una única interpretación? | C25: X
A26: 5 | B26: El modelo aplicado cumple con la sintaxis? | C26: X
A27: SUMATORIA: | C27: =COUNTA('LISTA DE COMPROBACION - CU0-0'!$C$22:$C$26) -> 5 | D27: =COUNTA('LISTA DE COMPROBACION - CU0-0'!$D$22:$D$26) -> 0
A28: PORCENTAJE : | C28: =C27/5 -> 1 | D28: =D27/5 -> 0
A30: NIVEL DE ACUERDO
A31: No. | B31: Pregunta | C31: SI | D31: NO
A32: 1 | B32: Todos los requerimientos han sido acordados con todos los interesados? | C32: X
A33: 2 | B33: Todos los requerimientos modificados han sido acordados por todos los implicados? | C33: X
A34: 3 | B34: Han sido resueltos todos los conflictos conocidos respectos de los requerimientos? | C34: X
A35: SUMATORIA: | C35: =COUNTA('LISTA DE COMPROBACION - CU0-0'!$C$32:$C$34) -> 3 | D35: =COUNTA('LISTA DE COMPROBACION - CU0-0'!$D$32:$D$34) -> 0
A36: PORCENTAJE : | C36: =C35/3 -> 1 | D36: =D35/3 -> 0
A40: RESUMEN
B41: CONTENIDO | C41: 89
B42: DOCUMENTACIÓN | C42: 100
B43: NIVEL DE ACUERDO | C43: 100

Sheet LISTA DE COMPROBACION - CU0-1
B1: SISTEMA: | C1: SISTEMA DE GESTIÓN DE PEDIDOS DEL RESTAURANTE BOCATTO VALLEY
B2: FECHA: | C2: 46300
B3: AUTOR: | C3: Laínez Suárez Ricardo Andrés
B4: REQUERIMIENTOS EVALUADOS : | C4: CU 0-1 Tomar pedido en mesa
A6: CONTENIDO
A7: No. | B7: Pregunta | C7: SI | D7: NO
A8: 1 | B8: Todos los requerimientos relevantes se han documentado? | C8: X
A9: 2 | B9: Se han implementado las funciones requeridas? | C9: X
A10: 3 | B10: Existe algún mecanismo que permita seguir el impacto de dicho requerimiento a lo largo del resto de las actividades del ciclo productivo.? | C10: X
A11: 4 | B11: El origen de cada requerimento individual está claro ? | C11: X
A12: 5 | B12: Que tan facil es devolverse a los requerimientos? | C12: X
A13: 6 | B13: Los requerimientos reflejan las necesidades y deseos del cliente? | C13: X
A14: 7 | B14: No hay contradicciones entre los requerimientos? | D14: x
A15: 8 | B15: El requerimiento que se esta especificando contribuye a alcanzar un objetivo definido ? | C15: X
A16: 9 | B16: Existe un proceso acotado (en plazo y presupuesto) que permita determinar que el sistema construido satisface lo descrito en el propio requerimiento? | C16: x
A17: SUMATORIA: | C17: =COUNTA('LISTA DE COMPROBACION - CU0-1'!$C$8:$C$16) -> 8 | D17: =COUNTA('LISTA DE COMPROBACION - CU0-1'!$D$8:$D$16) -> 1
A18: PORCENTAJE : | C18: =C17/9 -> 0.88888889 | D18: =D17/9 -> 0.11111111
A20: DOCUMENTACIÓN
A21: No. | B21: Pregunta | C21: SI | D21: NO
A22: 1 | B22: Aplica un estandar para la documetación de requerimiento? | C22: X
A23: 2 | B23: Cumple con la estructura definida por el estandar? | C23: X
A24: 3 | B24: Utiliza un Glosario de términos normalizado? | C24: X
A25: 4 | B25: Los requerimientos Funcionales estan sujetos a una única interpretación? | C25: X
A26: 5 | B26: El modelo aplicado cumple con la sintaxis? | C26: X
A27: SUMATORIA: | C27: =COUNTA('LISTA DE COMPROBACION - CU0-1'!$C$22:$C$26) -> 5 | D27: =COUNTA('LISTA DE COMPROBACION - CU0-1'!$D$22:$D$26) -> 0
A28: PORCENTAJE : | C28: =C27/5 -> 1 | D28: =D27/5 -> 0
A30: NIVEL DE ACUERDO
A31: No. | B31: Pregunta | C31: SI | D31: NO
A32: 1 | B32: Todos los requerimientos han sido acordados con todos los interesados? | C32: X
A33: 2 | B33: Todos los requerimientos modificados han sido acordados por todos los implicados? | C33: X
A34: 3 | B34: Han sido resueltos todos los conflictos conocidos respectos de los requerimientos? | C34: X
A35: SUMATORIA: | C35: =COUNTA('LISTA DE COMPROBACION - CU0-1'!$C$32:$C$34) -> 3 | D35: =COUNTA('LISTA DE COMPROBACION - CU0-1'!$D$32:$D$34) -> 0
A36: PORCENTAJE : | C36: =C35/3 -> 1 | D36: =D35/3 -> 0
A40: RESUMEN
B41: CONTENIDO | C41: 89
B42: DOCUMENTACIÓN | C42: 100
B43: NIVEL DE ACUERDO | C43: 100

Sheet LISTA DE COMPROBACION - CU0-2
B1: SISTEMA: | C1: SISTEMA DE GESTIÓN DE PEDIDOS DEL RESTAURANTE BOCATTO VALLEY
B2: FECHA: | C2: 46306
B3: AUTOR: | C3: Padilla Triviño Marco Adrian
B4: REQUERIMIENTOS EVALUADOS : | C4: CU 0-2 Tomar pedido telefónico
A6: CONTENIDO
A7: No. | B7: Pregunta | C7: SI | D7: NO
A8: 1 | B8: Todos los requerimientos relevantes se han documentado? | C8: X
A9: 2 | B9: Se han implementado las funciones requeridas? | C9: X
A10: 3 | B10: Existe algún mecanismo que permita seguir el impacto de dicho requerimiento a lo largo del resto de las actividades del ciclo productivo.? | C10: X
A11: 4 | B11: El origen de cada requerimento individual está claro ? | C11: X
A12: 5 | B12: Que tan facil es devolverse a los requerimientos? | C12: X
A13: 6 | B13: Los requerimientos reflejan las necesidades y deseos del cliente? | C13: X
A14: 7 | B14: No hay contradicciones entre los requerimientos? | D14: X
A15: 8 | B15: El requerimiento que se esta especificando contribuye a alcanzar un objetivo definido ? | C15: X
A16: 9 | B16: Existe un proceso acotado (en plazo y presupuesto) que permita determinar que el sistema construido satisface lo descrito en el propio requerimiento? | D16: X
A17: SUMATORIA: | C17: =COUNTA('LISTA DE COMPROBACION - CU0-2'!$C$8:$C$16) -> 7 | D17: =COUNTA('LISTA DE COMPROBACION - CU0-2'!$D$8:$D$16) -> 2
A18: PORCENTAJE : | C18: =C17/9 -> 0.77777778 | D18: =D17/9 -> 0.22222222
A20: DOCUMENTACIÓN
A21: No. | B21: Pregunta | C21: SI | D21: NO
A22: 1 | B22: Aplica un estandar para la documetación de requerimiento? | C22: X
A23: 2 | B23: Cumple con la estructura definida por el estandar? | C23: X
A24: 3 | B24: Utiliza un Glosario de términos normalizado? | C24: X
A25: 4 | B25: Los requerimientos Funcionales estan sujetos a una única interpretación? | D25: X
A26: 5 | B26: El modelo aplicado cumple con la sintaxis? | C26: X
A27: SUMATORIA: | C27: =COUNTA('LISTA DE COMPROBACION - CU0-2'!$C$22:$C$26) -> 4 | D27: =COUNTA('LISTA DE COMPROBACION - CU0-2'!$D$22:$D$26) -> 1
A28: PORCENTAJE : | C28: =C27/5 -> 0.8 | D28: =D27/5 -> 0.2
A30: NIVEL DE ACUERDO
A31: No. | B31: Pregunta | C31: SI | D31: NO
A32: 1 | B32: Todos los requerimientos han sido acordados con todos los interesados? | C32: X
A33: 2 | B33: Todos los requerimientos modificados han sido acordados por todos los implicados? | C33: X
A34: 3 | B34: Han sido resueltos todos los conflictos conocidos respectos de los requerimientos? | C34: X
A35: SUMATORIA: | C35: =COUNTA('LISTA DE COMPROBACION - CU0-2'!$C$32:$C$34) -> 3 | D35: =COUNTA('LISTA DE COMPROBACION - CU0-2'!$D$32:$D$34) -> 0
A36: PORCENTAJE : | C36: =C35/3 -> 1 | D36: =D35/3 -> 0
A40: RESUMEN
B41: CONTENIDO | C41: 78
B42: DOCUMENTACIÓN | C42: 80
B43: NIVEL DE ACUERDO | C43: 100

Sheet LISTA DE COMPROBACION - CU0-3
B1: SISTEMA: | C1: SISTEMA DE GESTIÓN DE PEDIDOS DEL RESTAURANTE BOCATTO VALLEY
B2: FECHA: | C2: 46306
B3: AUTOR: | C3: Padilla Triviño Marco Adrian
B4: REQUERIMIENTOS EVALUADOS : | C4: CU 0-3 Realizar pedido por QR
A6: CONTENIDO
A7: No. | B7: Pregunta | C7: SI | D7: NO
A8: 1 | B8: Todos los requerimientos relevantes se han documentado? | C8: X
A9: 2 | B9: Se han implementado las funciones requeridas? | C9: X
A10: 3 | B10: Existe algún mecanismo que permita seguir el impacto de dicho requerimiento a lo largo del resto de las actividades del ciclo productivo.? | C10: X
A11: 4 | B11: El origen de cada requerimento individual está claro ? | C11: X
A12: 5 | B12: Que tan facil es devolverse a los requerimientos? | C12: X
A13: 6 | B13: Los requerimientos reflejan las necesidades y deseos del cliente? | C13: X
A14: 7 | B14: No hay contradicciones entre los requerimientos? | C14: X
A15: 8 | B15: El requerimiento que se esta especificando contribuye a alcanzar un objetivo definido ? | C15: X
A16: 9 | B16: Existe un proceso acotado (en plazo y presupuesto) que permita determinar que el sistema construido satisface lo descrito en el propio requerimiento? | D16: X
A17: SUMATORIA: | C17: =COUNTA('LISTA DE COMPROBACION - CU0-3'!$C$8:$C$16) -> 8 | D17: =COUNTA('LISTA DE COMPROBACION - CU0-3'!$D$8:$D$16) -> 1
A18: PORCENTAJE : | C18: =C17/9 -> 0.88888889 | D18: =D17/9 -> 0.11111111
A20: DOCUMENTACIÓN
A21: No. | B21: Pregunta | C21: SI | D21: NO
A22: 1 | B22: Aplica un estandar para la documetación de requerimiento? | C22: X
A23: 2 | B23: Cumple con la estructura definida por el estandar? | C23: X
A24: 3 | B24: Utiliza un Glosario de términos normalizado? | C24: X
A25: 4 | B25: Los requerimientos Funcionales estan sujetos a una única interpretación? | C25: X
A26: 5 | B26: El modelo aplicado cumple con la sintaxis? | C26: X
A27: SUMATORIA: | C27: =COUNTA('LISTA DE COMPROBACION - CU0-3'!$C$22:$C$26) -> 5 | D27: =COUNTA('LISTA DE COMPROBACION - CU0-3'!$D$22:$D$26) -> 0
A28: PORCENTAJE : | C28: =C27/5 -> 1 | D28: =D27/5 -> 0
A30: NIVEL DE ACUERDO
A31: No. | B31: Pregunta | C31: SI | D31: NO
A32: 1 | B32: Todos los requerimientos han sido acordados con todos los interesados? | C32: X
A33: 2 | B33: Todos los requerimientos modificados han sido acordados por todos los implicados? | C33: X
A34: 3 | B34: Han sido resueltos todos los conflictos conocidos respectos de los requerimientos? | C34: X
A35: SUMATORIA: | C35: =COUNTA('LISTA DE COMPROBACION - CU0-3'!$C$32:$C$34) -> 3 | D35: =COUNTA('LISTA DE COMPROBACION - CU0-3'!$D$32:$D$34) -> 0
A36: PORCENTAJE : | C36: =C35/3 -> 1 | D36: =D35/3 -> 0
A40: RESUMEN
B41: CONTENIDO | C41: 89
B42: DOCUMENTACIÓN | C42: 100
B43: NIVEL DE ACUERDO | C43: 100

Sheet LISTA DE COMPROBACION - CU0-4
B1: SISTEMA: | C1: SISTEMA DE GESTIÓN DE PEDIDOS DEL RESTAURANTE BOCATTO VALLEY
B2: FECHA: | C2: 46300
B3: AUTOR: | C3: Andino Martínez Nelson David
B4: REQUERIMIENTOS EVALUADOS : | C4: CU 0-4 Gestionar preparación del pedido
A6: CONTENIDO
A7: No. | B7: Pregunta | C7: SI | D7: NO
A8: 1 | B8: Todos los requerimientos relevantes se han documentado? | C8: X
A9: 2 | B9: Se han implementado las funciones requeridas? | C9: X
A10: 3 | B10: Existe algún mecanismo que permita seguir el impacto de dicho requerimiento a lo largo del resto de las actividades del ciclo productivo.? | C10: X
A11: 4 | B11: El origen de cada requerimento individual está claro ? | C11: X
A12: 5 | B12: Que tan facil es devolverse a los requerimientos? | C12: X
A13: 6 | B13: Los requerimientos reflejan las necesidades y deseos del cliente? | C13: X
A14: 7 | B14: No hay contradicciones entre los requerimientos? | D14: X
A15: 8 | B15: El requerimiento que se esta especificando contribuye a alcanzar un objetivo definido ? | C15: X
A16: 9 | B16: Existe un proceso acotado (en plazo y presupuesto) que permita determinar que el sistema construido satisface lo descrito en el propio requerimiento? | D16: X
A17: SUMATORIA: | C17: =COUNTA('LISTA DE COMPROBACION - CU0-4'!$C$8:$C$16) -> 7 | D17: =COUNTA('LISTA DE COMPROBACION - CU0-4'!$D$8:$D$16) -> 2
A18: PORCENTAJE : | C18: =C17/9 -> 0.77777778 | D18: =D17/9 -> 0.22222222
A20: DOCUMENTACIÓN
A21: No. | B21: Pregunta | C21: SI | D21: NO
A22: 1 | B22: Aplica un estandar para la documetación de requerimiento? | C22: X
A23: 2 | B23: Cumple con la estructura definida por el estandar? | C23: X
A24: 3 | B24: Utiliza un Glosario de términos normalizado? | C24: X
A25: 4 | B25: Los requerimientos Funcionales estan sujetos a una única interpretación? | D25: X
A26: 5 | B26: El modelo aplicado cumple con la sintaxis? | C26: X
A27: SUMATORIA: | C27: =COUNTA('LISTA DE COMPROBACION - CU0-4'!$C$22:$C$26) -> 4 | D27: =COUNTA('LISTA DE COMPROBACION - CU0-4'!$D$22:$D$26) -> 1
A28: PORCENTAJE : | C28: =C27/5 -> 0.8 | D28: =D27/5 -> 0.2
A30: NIVEL DE ACUERDO
A31: No. | B31: Pregunta | C31: SI | D31: NO
A32: 1 | B32: Todos los requerimientos han sido acordados con todos los interesados? | C32: X
A33: 2 | B33: Todos los requerimientos modificados han sido acordados por todos los implicados? | C33: X
A34: 3 | B34: Han sido resueltos todos los conflictos conocidos respectos de los requerimientos? | C34: X
A35: SUMATORIA: | C35: =COUNTA('LISTA DE COMPROBACION - CU0-4'!$C$32:$C$34) -> 3 | D35: =COUNTA('LISTA DE COMPROBACION - CU0-4'!$D$32:$D$34) -> 0
A36: PORCENTAJE : | C36: =C35/3 -> 1 | D36: =D35/3 -> 0
A40: RESUMEN
B41: CONTENIDO | C41: 78
B42: DOCUMENTACIÓN | C42: 80
B43: NIVEL DE ACUERDO | C43: 100

Sheet LISTA DE COMPROBACION - CU0-5
B1: SISTEMA: | C1: SISTEMA DE GESTIÓN DE PEDIDOS DEL RESTAURANTE BOCATTO VALLEY
B2: FECHA: | C2: 46306
B3: AUTOR: | C3: Padilla Triviño Marco Adrian
B4: REQUERIMIENTOS EVALUADOS : | C4: CU 0-5 Cobrar pedido en la caja
A6: CONTENIDO
A7: No. | B7: Pregunta | C7: SI | D7: NO
A8: 1 | B8: Todos los requerimientos relevantes se han documentado? | C8: X
A9: 2 | B9: Se han implementado las funciones requeridas? | C9: X
A10: 3 | B10: Existe algún mecanismo que permita seguir el impacto de dicho requerimiento a lo largo del resto de las actividades del ciclo productivo.? | C10: X
A11: 4 | B11: El origen de cada requerimento individual está claro ? | C11: X
A12: 5 | B12: Que tan facil es devolverse a los requerimientos? | C12: X
A13: 6 | B13: Los requerimientos reflejan las necesidades y deseos del cliente? | C13: X
A14: 7 | B14: No hay contradicciones entre los requerimientos? | D14: X
A15: 8 | B15: El requerimiento que se esta especificando contribuye a alcanzar un objetivo definido ? | C15: X
A16: 9 | B16: Existe un proceso acotado (en plazo y presupuesto) que permita determinar que el sistema construido satisface lo descrito en el propio requerimiento? | D16: X
A17: SUMATORIA: | C17: =COUNTA('LISTA DE COMPROBACION - CU0-5'!$C$8:$C$16) -> 7 | D17: =COUNTA('LISTA DE COMPROBACION - CU0-5'!$D$8:$D$16) -> 2
A18: PORCENTAJE : | C18: =C17/9 -> 0.77777778 | D18: =D17/9 -> 0.22222222
A20: DOCUMENTACIÓN
A21: No. | B21: Pregunta | C21: SI | D21: NO
A22: 1 | B22: Aplica un estandar para la documetación de requerimiento? | C22: X
A23: 2 | B23: Cumple con la estructura definida por el estandar? | C23: X
A24: 3 | B24: Utiliza un Glosario de términos normalizado? | C24: X
A25: 4 | B25: Los requerimientos Funcionales estan sujetos a una única interpretación? | C25: X
A26: 5 | B26: El modelo aplicado cumple con la sintaxis? | C26: X
A27: SUMATORIA: | C27: =COUNTA('LISTA DE COMPROBACION - CU0-5'!$C$22:$C$26) -> 5 | D27: =COUNTA('LISTA DE COMPROBACION - CU0-5'!$D$22:$D$26) -> 0
A28: PORCENTAJE : | C28: =C27/5 -> 1 | D28: =D27/5 -> 0
A30: NIVEL DE ACUERDO
A31: No. | B31: Pregunta | C31: SI | D31: NO
A32: 1 | B32: Todos los requerimientos han sido acordados con todos los interesados? | C32: X
A33: 2 | B33: Todos los requerimientos modificados han sido acordados por todos los implicados? | C33: X
A34: 3 | B34: Han sido resueltos todos los conflictos conocidos respectos de los requerimientos? | C34: X
A35: SUMATORIA: | C35: =COUNTA('LISTA DE COMPROBACION - CU0-5'!$C$32:$C$34) -> 3 | D35: =COUNTA('LISTA DE COMPROBACION - CU0-5'!$D$32:$D$34) -> 0
A36: PORCENTAJE : | C36: =C35/3 -> 1 | D36: =D35/3 -> 0
A40: RESUMEN
B41: CONTENIDO | C41: 78
B42: DOCUMENTACIÓN | C42: 100
B43: NIVEL DE ACUERDO | C43: 100

Sheet RECOMENDACIONES - CU 0-0
A1: PREGUNTA | B1: RECOMENDACIÓN | C1: RESPONSABLE
A2: ¿Se han validado y aprobado formalmente todos los entregables de la entrevista (videoconferencia, minuta, acta de aceptación)? | B2: Se ha validado todos lo entregables de las entrevista, sin embargo se recomienda que todos los implicados, mas en la minuta, hayan podido firmar. | C2: Laínez Suárez Ricardo Andrés
A3: ¿Se han definido criterios de aceptación y casos de prueba que permitan medir objetivamente el cumplimiento del requisito? | B3: Apesar de que existen criterios de calidad, tanto como criterios de aceptacion y casos de prueba no se muestran como un proceso de la gestin de requerimientos, se recomienda implementar esto para mejorar el cumplimiento del requisito | C3: Laínez Suárez Ricardo Andrés

Sheet RECOMENDACIONES - CU 0-1
A1: PREGUNTA | B1: RECOMENDACIÓN | C1: RESPONSABLE
A2: ¿Se han validado y aprobado formalmente todos los entregables de la entrevista (videoconferencia, minuta, acta de aceptación)? | B2: Los entregables de las entrevistas fueron validados y aprobados por la lider del proyecto, sin embargo se recomienda notificar a la persona encargada, mesero, de lo aprobado del caso de uso | C2: Laínez Suárez Ricardo Andrés
A3: ¿Se han definido criterios de aceptación y casos de prueba que permitan medir objetivamente el cumplimiento del requisito? | B3: Apesar de que existen criterios de calidad, tanto como criterios de aceptacion y casos de prueba no se muestran como un proceso de la gestin de requerimientos, se recomienda implementar esto para mejorar el cumplimiento del requisito | C3: Laínez Suárez Ricardo Andrés

Sheet RECOMENDACIONES - CU 0-2
A1: PREGUNTA | B1: RECOMENDACIÓN | C1: RESPONSABLE
A2: ¿Los requerimientos funcionales están sujetos a una única interpretación? | B2: Definir en la fase de diseño, mediante el formulario de registro, los datos mínimos del pedido telefónico (nombre, teléfono y dirección o modalidad de retiro), tomando como base el CU 0-2 y el RF-03, sin modificar la ERS. | C2: Padilla Triviño Marco Adrian
A3: ¿No hay contradicciones entre los requerimientos? | B3: Incluir en el diseño una búsqueda alternativa al número de mesa (por ID del pedido o teléfono del cliente), para que caja pueda cobrar los pedidos telefónicos que el CU 0-5 no contempla. | C3: Padilla Triviño Marco Adrian
A4: ¿Existe un proceso acotado (en plazo y presupuesto) que permita determinar que el sistema construido satisface lo descrito en el requisito? | B4: Elaborar en el plan de pruebas tres casos para el RF-03: pedido sin productos, pedido con datos de entrega completos y pedido registrado con estado "pendiente" visible en cocina. | C4: Padilla Triviño Marco Adrian

Sheet RECOMENDACIONES - CU 0-3
A1: PREGUNTA | B1: RECOMENDACIÓN | C1: RESPONSABLE
A2: ¿Existe un proceso acotado (en plazo y presupuesto) que permita determinar que el sistema construido satisface lo descrito en el requisito? | B2: Elaborar en el plan de pruebas tres casos para el RF-04: QR no asociado a una mesa, intento de confirmar un pedido vacío y pedido confirmado con estado "pendiente". No requiere modificar la ERS. | C2: Padilla Triviño Marco Adrian
A3: ¿Se utilizan los términos de forma uniforme a lo largo del documento? | B3: Usar en los artefactos de diseño el nombre "Realizar pedido por QR" del CU 0-3, ya que en la sección 3.2.7 aparece como "Gestionar pedido por QR", para evitar confusiones al exponer o diseñar. | C3: Padilla Triviño Marco Adrian

Sheet RECOMENDACIONES - CU 0-4
A1: PREGUNTA | B1: RECOMENDACIÓN | C1: RESPONSABLE
A2: ¿Los requerimientos funcionales están sujetos a una única interpretación? | B2: Tomar como referencia en el diseño de la pantalla de cocina la secuencia cerrada de estados del RF-05 (pendiente, en preparación, listo y listo para entregar) y no la lista abierta con "por ejemplo" del CU 0-4. | C2: Andino Martínez Nelson David
A3: ¿No hay contradicciones entre los requerimientos? | B3: Acordar dentro del equipo que el estado "listo para entregar" se habilita después del pago, como indica el CU 0-5, y dejarlo anotado en el diagrama de estados del pedido durante la fase de diseño. | C3: Andino Martínez Nelson David
A4: ¿Existe un proceso acotado (en plazo y presupuesto) que permita determinar que el sistema construido satisface lo descrito en el requisito? | B4: Elaborar en la fase de pruebas casos de prueba para el RF-05 que confirmen que no se puede saltar un estado y que cada cambio queda visible para caja y cliente. | C4: Andino Martínez Nelson David

Sheet RECOMENDACIONES - CU 0-5
A1: PREGUNTA | B1: RECOMENDACIÓN | C1: RESPONSABLE
A2: ¿No hay contradicciones entre los requerimientos? | B2: Modelar en PlantUML el diagrama de estados del pedido con la secuencia completa (pendiente, en preparación, listo, pagado, listo para entregar) y fijar que "listo para entregar" se habilita tras el pago, alineando el CU 0-4, el CU 0-5 y el RF-05 en la fase de diseño. | C2: Padilla Triviño Marco Adrian
A3: ¿Existe un proceso acotado (en plazo y presupuesto) que permita determinar que el sistema construido satisface lo descrito en el requisito? | B3: Elaborar en el plan de pruebas casos para el RF-06: intento de cobrar un pedido que no está listo, cobro en efectivo, cobro digital y verificación del estado "pagado". | C3: Padilla Triviño Marco Adrian
